LabGym/COPYRIGHT.txt
LabGym/NOTICE.txt
LabGym/__init__.py
LabGym/__main__.py
LabGym/analyzebehavior.py
LabGym/analyzebehavior_dt.py
LabGym/categorizer.py
LabGym/central_logging.py
LabGym/config.py
LabGym/detector.py
LabGym/detectors/__init__.py
LabGym/detectron2/__init__.py
LabGym/detectron2/checkpoint/__init__.py
LabGym/detectron2/checkpoint/c2_model_loading.py
LabGym/detectron2/checkpoint/catalog.py
LabGym/detectron2/checkpoint/detection_checkpoint.py
LabGym/detectron2/config/__init__.py
LabGym/detectron2/config/compat.py
LabGym/detectron2/config/config.py
LabGym/detectron2/config/defaults.py
LabGym/detectron2/config/instantiate.py
LabGym/detectron2/config/lazy.py
LabGym/detectron2/data/__init__.py
LabGym/detectron2/data/benchmark.py
LabGym/detectron2/data/build.py
LabGym/detectron2/data/catalog.py
LabGym/detectron2/data/common.py
LabGym/detectron2/data/dataset_mapper.py
LabGym/detectron2/data/datasets/__init__.py
LabGym/detectron2/data/datasets/builtin.py
LabGym/detectron2/data/datasets/builtin_meta.py
LabGym/detectron2/data/datasets/cityscapes.py
LabGym/detectron2/data/datasets/cityscapes_panoptic.py
LabGym/detectron2/data/datasets/coco.py
LabGym/detectron2/data/datasets/coco_panoptic.py
LabGym/detectron2/data/datasets/lvis.py
LabGym/detectron2/data/datasets/lvis_v0_5_categories.py
LabGym/detectron2/data/datasets/lvis_v1_categories.py
LabGym/detectron2/data/datasets/lvis_v1_category_image_count.py
LabGym/detectron2/data/datasets/pascal_voc.py
LabGym/detectron2/data/datasets/register_coco.py
LabGym/detectron2/data/detection_utils.py
LabGym/detectron2/data/samplers/__init__.py
LabGym/detectron2/data/samplers/distributed_sampler.py
LabGym/detectron2/data/samplers/grouped_batch_sampler.py
LabGym/detectron2/data/transforms/__init__.py
LabGym/detectron2/data/transforms/augmentation.py
LabGym/detectron2/data/transforms/augmentation_impl.py
LabGym/detectron2/data/transforms/transform.py
LabGym/detectron2/engine/__init__.py
LabGym/detectron2/engine/defaults.py
labgym-2.9.6.dist-info/METADATA
labgym-2.9.6.dist-info/WHEEL
labgym-2.9.6.dist-info/entry_points.txt
labgym-2.9.6.dist-info/licenses/LICENSE.txt
labgym-2.9.6.dist-info/licenses/NOTICE.txt
labgym-2.9.6.dist-info/RECORD
