Metadata-Version: 2.1
Name: LabGym
Version: 2.9.6
Summary: Quantify user-defined behaviors.
Keywords: behavior analysis,user defined behaviors,behavior quantification
Author-Email: Yujia Hu <yujiahu415@gmail.com>, Rohan Satapathy <rohansat@umich.edu>, John Ruckstuhl <john.ruckstuhl@gmail.com>, "M. Victor Struman" <strmark@umich.edu>, Kelly Goss <khgoss@umich.edu>, Isabelle Baker <ibaker@umich.edu>
License: GPL-3.0
Classifier: License :: OSI Approved :: GNU General Public License v3 (GPLv3)
Classifier: Operating System :: OS Independent
Classifier: Programming Language :: Python :: 3
Classifier: Programming Language :: Python :: 3 :: Only
Classifier: Programming Language :: Python :: 3.9
Classifier: Programming Language :: Python :: 3.10
Project-URL: Homepage, http://github.com/umyelab/LabGym
Project-URL: Documentation, https://labgym.readthedocs.io/en/latest/
Project-URL: Issues, http://github.com/umyelab/LabGym/issues
Requires-Python: <3.11,>=3.9
Requires-Dist: tensorflow<2.16.0,>=2.10.1; platform_system != "Windows"
Requires-Dist: tensorflow<2.11; platform_system == "Windows"
Requires-Dist: matplotlib
Requires-Dist: opencv-python
Requires-Dist: opencv-contrib-python
Requires-Dist: openpyxl
Requires-Dist: xlsxwriter
Requires-Dist: pandas
Requires-Dist: scikit-learn
Requires-Dist: scikit-image
Requires-Dist: seaborn
Requires-Dist: wxPython
Requires-Dist: scikit-posthocs
Requires-Dist: packaging
Requires-Dist: requests
Requires-Dist: numpy<=1.26.4
Requires-Dist: torch
Requires-Dist: torchvision
Requires-Dist: torchaudio
Requires-Dist: PyYAML
Requires-Dist: tomli
Requires-Dist: Pillow>=7.1
Requires-Dist: matplotlib
Requires-Dist: pycocotools>=2.0.2
Requires-Dist: termcolor>=1.1
Requires-Dist: yacs>=0.1.8
Requires-Dist: tabulate
Requires-Dist: cloudpickle
Requires-Dist: tqdm>4.29.0
Requires-Dist: tensorboard
Requires-Dist: fvcore<0.1.6,>=0.1.5
Requires-Dist: iopath<=0.1.10,>=0.1.7
Requires-Dist: dataclasses; python_version < "3.7"
Requires-Dist: omegaconf<2.4,>=2.1
Requires-Dist: hydra-core>=1.1
Requires-Dist: black
Requires-Dist: ninja
Requires-Dist: six
Requires-Dist: pyobjc-framework-Cocoa; platform_system == "Darwin"
